berteome/__init__.py
berteome/_nbdev.py
berteome/berteome.py
berteome/berteomeDF.py
berteome/core.py
berteome/esm.py
berteome/esm1b.py
berteome/prot_bert.py
berteome-0.1.6.dist-info/LICENSE
berteome-0.1.6.dist-info/METADATA
berteome-0.1.6.dist-info/WHEEL
berteome-0.1.6.dist-info/entry_points.txt
berteome-0.1.6.dist-info/top_level.txt
berteome-0.1.6.dist-info/RECORD
