Metadata-Version: 2.1
Name: berteome
Version: 0.1.6
Summary: A library to analyze and explore protein sequences using BERT models
Home-page: https://github.com/tijeco/berteome/tree/{branch}/
Author: T. Jeffrey Cole
Author-email: jffcole7@gmail.com
License: Apache Software License 2.0
Keywords: python,BERT,protein,bioinformatics,proteomics
Platform: UNKNOWN
Classifier: Development Status :: 3 - Alpha
Classifier: Intended Audience :: Developers
Classifier: Natural Language :: English
Classifier: Programming Language :: Python :: 3.6
Classifier: Programming Language :: Python :: 3.7
Classifier: Programming Language :: Python :: 3.8
Classifier: License :: OSI Approved :: Apache Software License
Requires-Python: >=3.6
Requires-Dist: pip
Requires-Dist: packaging
Requires-Dist: pandas
Requires-Dist: numpy
Requires-Dist: seqlogo
Requires-Dist: transformers (==4.10.0)
Requires-Dist: datasets (==1.11.0)
Requires-Dist: torch
Requires-Dist: torchvision
Requires-Dist: fair-esm
Provides-Extra: dev
